utilss/__init__.py
utilss/getMax.py
utilss/getMin.py
utilss-0.1.7.dist-info/METADATA
utilss-0.1.7.dist-info/WHEEL
utilss-0.1.7.dist-info/top_level.txt
utilss-0.1.7.dist-info/RECORD
