Metadata-Version: 2.1
Name: utilss
Version: 0.1.7
Summary: Useful tools to work with text mining in Python
Home-page: https://github.com/xiaoouwang/utilss
Author: Xiaoou WANG
Author-email: xiaoouwangfrance@gmail.com
License: MIT
Download-URL: https://pypi.org/project/utilss
Keywords: text mining,npl,corpus
Platform: UNKNOWN
Classifier: Programming Language :: Python :: 3
Classifier: License :: OSI Approved :: MIT License
Classifier: Operating System :: OS Independent
